search_sampler/__init__.py
search_sampler/example.py
search_sampler-1.0.1.dist-info/METADATA
search_sampler-1.0.1.dist-info/RECORD
search_sampler-1.0.1.dist-info/WHEEL
search_sampler-1.0.1.dist-info/top_level.txt
