Metadata-Version: 2.1
Name: search-sampler
Version: 1.0.1
Summary: UNKNOWN
Home-page: https://github.com/pewresearch/search_sampler
Author: Pew Research Center
Author-email: info@pewresearch.org
License: MIT
Keywords: google,sampling,trends
Platform: UNKNOWN
Classifier: Development Status :: 5 - Production/Stable
Classifier: Intended Audience :: Science/Research
Classifier: Topic :: Software Development :: Libraries :: Python Modules
Classifier: License :: OSI Approved :: MIT License
Classifier: Programming Language :: Python :: 2.7
Requires-Dist: google-api-python-client (==1.6.5)
Requires-Dist: pandas (>=0.2.0)
